iterify/__init__.py
iterify/cyclify.py
iterify/iterify.py
iterify/samplify.py
iterify/shufflify.py
iterify-0.1.0.dist-info/AUTHORS.rst
iterify-0.1.0.dist-info/LICENSE
iterify-0.1.0.dist-info/METADATA
iterify-0.1.0.dist-info/WHEEL
iterify-0.1.0.dist-info/top_level.txt
iterify-0.1.0.dist-info/RECORD
