Metadata-Version: 2.1
Name: iterify
Version: 0.1.0
Summary: iterify streamlines making one-off iterators over one or a few values
Home-page: https://github.com/mmore500/iterify
Author: Matthew Andres Moreno
Author-email: m.more500@gmail.com
License: MIT license
Keywords: iterify
Platform: UNKNOWN
Classifier: Development Status :: 2 - Pre-Alpha
Classifier: Intended Audience :: Developers
Classifier: License :: OSI Approved :: MIT License
Classifier: Natural Language :: English
Classifier: Programming Language :: Python :: 3
Classifier: Programming Language :: Python :: 3.6
Classifier: Programming Language :: Python :: 3.7
Classifier: Programming Language :: Python :: 3.8
Requires-Python: >=3.6
